tfbs_footprinter3/__init__.py
tfbs_footprinter3/tfbs_footprinter3.py
tfbs_footprinter3/data/pwms.json
tfbs_footprinter3/data/species_nt_freq.json
tfbs_footprinting3-0.0.7.dist-info/licenses/LICENSE
tfbs_footprinting3-0.0.7.dist-info/METADATA
tfbs_footprinting3-0.0.7.dist-info/WHEEL
tfbs_footprinting3-0.0.7.dist-info/entry_points.txt
tfbs_footprinting3-0.0.7.dist-info/top_level.txt
tfbs_footprinting3-0.0.7.dist-info/RECORD
