Metadata-Version: 2.4
Name: TFBS_footprinting3
Version: 0.0.7
Summary: Tool for identifying conserved TFBSs in vertebrate species.
Home-page: https://github.com/thirtysix/TFBS_footprinting3
Author: Harlan Barker
Author-email: Harlan Barker <harlan.barker@tuni.fi>
License: MIT
Project-URL: Homepage, https://github.com/thirtysix/TFBS_footprinting3
Keywords: bioinformatics,analysis
Classifier: Development Status :: 4 - Beta
Classifier: Intended Audience :: Science/Research
Classifier: Topic :: Scientific/Engineering :: Bio-Informatics
Classifier: License :: OSI Approved :: MIT License
Classifier: Programming Language :: Python :: 3
Classifier: Programming Language :: Python :: 3.7
Classifier: Programming Language :: Python :: 3.8
Requires-Python: >=3.7
License-File: LICENSE
Requires-Dist: httplib2
Requires-Dist: numpy
Requires-Dist: matplotlib
Requires-Dist: biopython
Requires-Dist: msgpack
Requires-Dist: wget
Requires-Dist: pandas
Dynamic: author
Dynamic: home-page
Dynamic: license-file
